fastapi_keycloak_sso/__init__.py
fastapi_keycloak_sso/auth.py
fastapi_keycloak_sso/decorators.py
fastapi_keycloak_sso/initializer.py
fastapi_keycloak_sso/keycloak.py
fastapi_keycloak_sso/permissions.py
fastapi_keycloak_sso/api/__init__.py
fastapi_keycloak_sso/api/enums.py
fastapi_keycloak_sso/api/schemas.py
fastapi_keycloak_sso/api/routers/base_routers.py
fastapi_keycloak_sso/sso/__init__.py
fastapi_keycloak_sso/sso/authenticate.py
fastapi_keycloak_sso/sso/caching.py
fastapi_keycloak_sso/sso/exceptions.py
fastapi_keycloak_sso/sso/fields.py
fastapi_keycloak_sso/sso/helpers.py
fastapi_keycloak_sso/sso/schemas.py
fastapi_keycloak_sso/sso/sso.py
fastapi_keycloak_sso/sso/utils.py
fastapi_keycloak_sso-0.0.9.dist-info/licenses/LICENCE
fastapi_keycloak_sso-0.0.9.dist-info/METADATA
fastapi_keycloak_sso-0.0.9.dist-info/WHEEL
fastapi_keycloak_sso-0.0.9.dist-info/top_level.txt
fastapi_keycloak_sso-0.0.9.dist-info/RECORD
