Metadata-Version: 2.4
Name: fastapi-keycloak-sso
Version: 0.0.9
Summary: Reusable FastAPI app for SSO integration
Author-email: Yousef Haghighat <yousefmpym1@gmail.com>
Project-URL: Homepage, https://github.com/YousefHaghigaht/fastapi_keycloak_sso.git
Requires-Python: >=3.10
License-File: LICENCE
Requires-Dist: fastapi>=0.121.1
Requires-Dist: python-jose>=3.3.0
Requires-Dist: requests>=2.32.2
Requires-Dist: dotenv>=0.9.9
Requires-Dist: redis>=7.1.0
Requires-Dist: sqlalchemy>=2.0.44
Dynamic: license-file
